sctop/__init__.py
sctop/sctop.py
sctop/databases/data_LD_apr22.h5
sctop/databases/data_MC20_apr22.h5
sctop/databases/data_MCKO_apr22.h5
sctop/databases/metadata_LD_apr22.csv
sctop/databases/metadata_MC20_apr22.csv
sctop/databases/metadata_MCKO_apr22.csv
scTOP-1.0.0.dist-info/LICENSE.txt
scTOP-1.0.0.dist-info/METADATA
scTOP-1.0.0.dist-info/WHEEL
scTOP-1.0.0.dist-info/top_level.txt
scTOP-1.0.0.dist-info/RECORD
