Metadata-Version: 2.1
Name: scTOP
Version: 1.0.0
Summary: A package for identifying cell phenotype from single-cell RNA-sequencing data.
Home-page: https://github.com/Emergent-Behaviors-in-Biology/scTOP
Author: Maria Yampolskaya
Author-email: mariay@bu.edu
Project-URL: Bug Tracker, https://github.com/Emergent-Behaviors-in-Biology/scTOP/issues
Project-URL: Docs, https://sctop.readthedocs.io/
Classifier: Programming Language :: Python :: 3
Classifier: License :: OSI Approved :: GNU General Public License (GPL)
Classifier: Operating System :: OS Independent
Requires-Python: >=3.6
License-File: LICENSE.txt
Requires-Dist: numpy
Requires-Dist: pandas
Requires-Dist: scipy
Requires-Dist: tables
